{
  "name": "LewdGames",
  "downloads": [
    {
      "title": "NejicomiSimulator Volume 5 [By yabukaradoo]",
      "uploadDate": "2025-06-19T00:00:00+00:00",
      "fileSize": "154.7 MB",
      "uris": [
        "https://mega.nz/file/rV8yxZhR#1qBBuV9MZsTSOwlrrazqCyTv2JehjaXBeCLmiwChrcQ"
      ]
    },
    {
      "title": "NejicomiSimulator Volume 4 [By yabukaradoo]",
      "uploadDate": "2025-06-19T00:00:00+00:00",
      "fileSize": "109.5 MB",
      "uris": [
        "https://gofile.io/d/Ckc9pd"
      ]
    },
    {
      "title": "NejicomiSimulator Volume 3 [By yabukaradoo]",
      "uploadDate": "2025-06-19T00:00:00+00:00",
      "fileSize": "177 MB",
      "uris": [
        "https://pixeldrain.com/u/CsCfyQQR"
      ]
    },
    {
      "title": "NejicomiSimulator Volume 2 [By yabukaradoo]",
      "uploadDate": "2025-06-19T00:00:00+00:00",
      "fileSize": "106.2 MB",
      "uris": [
        "https://gofile.io/d/eht3Ch"
      ]
    },
    {
      "title": "NejicomiSimulator Volume 1 [By yabukaradoo]",
      "uploadDate": "2025-06-19T00:00:00+00:00",
      "fileSize": "59.2 MB",
      "uris": [
        "https://gofile.io/d/a4zgTt"
      ]
    },
    {
      "title": "NejicomiSimulator TMA02 – Turning a Rude, Titanic-Tittied Slut into Your Personal Heifer-Hole [v1.0.9 + DLC] By yabukaradoo",
      "uploadDate": "2025-06-19T00:00:00+00:00",
      "fileSize": "321.2 MB",
      "uris": [
        "https://mega.nz/file/4WVFRIbQ#3hzE-6cev2_rZVmGRA7VgG5eUqvfE6y6abnN4nfJ3kM"
      ]
    }
  ]
}
